mongo_to_s3/__init__.py
mongo_to_s3/mongo_to_s3.py
mongo_to_s3-0.0.9.dist-info/METADATA
mongo_to_s3-0.0.9.dist-info/WHEEL
mongo_to_s3-0.0.9.dist-info/entry_points.txt
mongo_to_s3-0.0.9.dist-info/licenses/LICENSE.txt
mongo_to_s3-0.0.9.dist-info/RECORD
