Metadata-Version: 2.1
Name: mongo-to-s3
Version: 0.0.9
Summary: Automated script generator to backup MongoDB databases to Amazon S3.
Project-URL: Homepage, https://github.com/IamLizu/mongo-to-s3
Project-URL: Bug Tracker, https://github.com/IamLizu/mongo-to-s3/issues
Author-email: S M Mahmudul Hasan <thegeek@iamlizu.com>
License-File: LICENSE.txt
Classifier: Development Status :: 4 - Beta
Classifier: License :: OSI Approved :: MIT License
Classifier: Operating System :: OS Independent
Classifier: Programming Language :: Python :: 3
Requires-Python: >=3.7
Requires-Dist: boto3
